MANIFEST.in
README.md
setup.cfg
setup.py
pyramid_debugtoolbar_api_sqla/__init__.py
pyramid_debugtoolbar_api_sqla.egg-info/PKG-INFO
pyramid_debugtoolbar_api_sqla.egg-info/SOURCES.txt
pyramid_debugtoolbar_api_sqla.egg-info/dependency_links.txt
pyramid_debugtoolbar_api_sqla.egg-info/not-zip-safe
pyramid_debugtoolbar_api_sqla.egg-info/requires.txt
pyramid_debugtoolbar_api_sqla.egg-info/top_level.txt