Metadata-Version: 1.1
Name: pyramid-debugtoolbar-api-sqla
Version: 0.0.2
Summary: sqlalchmey exporting for pyramid_debugtoolbar
Home-page: https://github.com/jvanasco/pyramid_debugtoolbar_api_sqla
Author: Jonathan Vanasco
Author-email: jonathan@findmeon.com
License: MIT
Keywords: web pyramid
Platform: UNKNOWN
Classifier: Intended Audience :: Developers
Classifier: Framework :: Pyramid
Classifier: Programming Language :: Python
Classifier: License :: OSI Approved :: MIT License
